pjdev_va_ois_emass_api_client/__about__.py
pjdev_va_ois_emass_api_client/__init__.py
pjdev_va_ois_emass_api_client/emass_service.py
pjdev_va_ois_emass_api_client/settings.py
pjdev_va_ois_emass_api_client/validators.py
pjdev_va_ois_emass_api_client/models/__init__.py
pjdev_va_ois_emass_api_client/models/common.py
pjdev_va_ois_emass_api_client/models/dashboard_models.py
pjdev_va_ois_emass_api_client/models/emass_models.py
pjdev_va_ois_emass_api_client-0.0.9.dist-info/METADATA
pjdev_va_ois_emass_api_client-0.0.9.dist-info/WHEEL
pjdev_va_ois_emass_api_client-0.0.9.dist-info/licenses/LICENSE.txt
pjdev_va_ois_emass_api_client-0.0.9.dist-info/RECORD
